{
  "name": {
    "ar": "Ø¢ÙØ§Ù‚",
    "en": "Afaq"
  },
  "repository": "https://github.com/foalmalki/salla-theme",
  "author_email": "support@example.com",
  "features": [
    "mega-menu",
    "fonts",
    "color",
    "breadcrumb",
    "filters"
  ],
  "settings": [
    {
      "type": "boolean",
      "id": "sticky_header",
      "label": "Sticky Header",
      "format": "switch",
      "required": false,
      "value": true,
      "selected": true
    },
    {
      "type": "string",
      "id": "placeholder",
      "label": "Placeholder",
      "format": "hidden",
      "value": "images/img_placeholder.png",
      "required": false
    }
  ],
  "components": [
    {
      "key": "1f6f1be3-0c3d-4bda-9f7f-8a37724b4b91",
      "title": {
        "ar": "ØµÙˆØ± Ù…ØªØ­Ø±ÙƒØ© (Ù…Ø­Ø³Ù†Ø©)",
        "en": "Enhanced Slider"
      },
      "icon": "sicon-image-carousel",
      "path": "home.enhanced-slider",
      "image": null,
      "fields": []
    },
    {
      "key": "904be89a-28e7-4d2e-a8b4-72eec7cf6ff8",
      "title": {
        "ar": "Ø±ÙˆØ§Ø¨Ø· Ø³Ø±ÙŠØ¹Ø©",
        "en": "Main Links"
      },
      "icon": "sicon-grid",
      "path": "home.main-links",
      "image": null,
      "fields": []
    },
    {
      "key": "4d7cb556-79fd-4dd5-b573-15b5672a1a6e",
      "title": {
        "ar": "Ù…Ù†ØªØ¬Ø§Øª Ù…ØªØ­Ø±ÙƒØ© Ù…Ø¹ Ø®Ù„ÙÙŠØ©",
        "en": "Products Slider with Header"
      },
      "icon": "sicon-list-play",
      "path": "home.slider-products-with-header",
      "image": null,
      "fields": []
    },
    {
      "key": "7e07c2fc-00eb-458a-9697-d4b7f3b43ae5",
      "title": {
        "ar": "ØµÙˆØ± Ù…Ø±Ø¨Ø¹Ø© (Ù…Ø­Ø³Ù†Ø©)",
        "en": "Enhanced Square Banners"
      },
      "icon": "sicon-image",
      "path": "home.enhanced-square-banners",
      "image": null,
      "fields": []
    },
    {
      "key": "2f9bb8aa-5d43-4cde-a0c5-e7f1f6a1f050",
      "title": {
        "ar": "Ø§Ù„Ù…Ø§Ø±ÙƒØ§Øª Ø§Ù„ØªØ¬Ø§Ø±ÙŠØ©",
        "en": "Brands"
      },
      "icon": "sicon-award",
      "path": "home.brands",
      "image": null,
      "fields": []
    },
    {
      "key": "5b9e86f2-9ca5-4381-a8c5-a0f1f18c2204",
      "title": {
        "ar": "Ø¢Ø±Ø§Ø¡ Ø¹Ù…Ù„Ø§Ø¡ Ù…Ø®ØµØµØ©",
        "en": "Custom Testimonials"
      },
      "icon": "sicon-chat",
      "path": "home.custom-testimonials",
      "image": null,
      "fields": []
    }
  ]
}